surferpup/cli.py
surferpup/runner.py
surferpup/validate.py
surferpup-0.1.0.dist-info/METADATA
surferpup-0.1.0.dist-info/WHEEL
surferpup-0.1.0.dist-info/entry_points.txt
surferpup-0.1.0.dist-info/top_level.txt
surferpup-0.1.0.dist-info/RECORD
