Metadata-Version: 2.4
Name: surferpup
Version: 0.1.0
Summary: Safe localhost application stress testing tool
Requires-Python: >=3.9
Requires-Dist: aiohttp
Requires-Dist: colorama
